codified_json/__init__.py
codified_json/_object.py
codified_json/_structures.py
codified_json/_utils.py
codified_json-0.1.1.dist-info/LICENSE
codified_json-0.1.1.dist-info/METADATA
codified_json-0.1.1.dist-info/WHEEL
codified_json-0.1.1.dist-info/top_level.txt
codified_json-0.1.1.dist-info/RECORD
