Metadata-Version: 2.1
Name: codified-json
Version: 0.1.1
Summary: Codified-JSON - represent the same JSON data with less characters
Home-page: UNKNOWN
Author: Tim Huang
License: MIT
Platform: UNKNOWN
